miacag/__init__.py
miacag/features.py
miacag/predictor.py
miacag/tester.py
miacag/trainer.py
miacag/configs/__init__.py
miacag/configs/config.py
miacag/configs/options.py
miacag/configs/update_configs.py
miacag/configs/classification/__init__.py
miacag/configs/classification/_3D/__init__.py
miacag/configs/classification/_3D/lca_rca/__init__.py
miacag/configs/classification/_3D/lca_rca/classification_config_angio.yaml
miacag/configs/classification/_3D/stenosis_detection_rca/classification_config_angio.yaml
miacag/dataloader/DistributedWeightedSampler.py
miacag/dataloader/__init__.py
miacag/dataloader/dataloader_base.py
miacag/dataloader/dataloader_base_monai.py
miacag/dataloader/get_dataloader.py
miacag/dataloader/Classification/__init__.py
miacag/dataloader/Classification/get_dataloader_classification.py
miacag/dataloader/Classification/_2D/__init__.py
miacag/dataloader/Classification/_2D/dataloader_monai_classification_2D.py
miacag/dataloader/Classification/_2D/dataloader_monai_classification_2D_mil.py
miacag/dataloader/Classification/_2D/dataloader_monai_classification_2D_mil_fast.py
miacag/dataloader/Classification/_2D/dataset_mil_2d.py
miacag/dataloader/Classification/_3D/__init__.py
miacag/dataloader/Classification/_3D/dataloader_avi_video.py
miacag/dataloader/Classification/_3D/dataloader_monai_classification_3D.py
miacag/dataloader/Classification/_3D/dataloader_monai_classification_3D_mil.py
miacag/dataloader/Classification/_3D/dataset_mil.py
miacag/dataloader/Representation/__init__.py
miacag/dataloader/Representation/get_dataloader_representation.py
miacag/metrics/__init__.py
miacag/metrics/cumulativeSumming.py
miacag/metrics/metrics.py
miacag/metrics/metrics_utils.py
miacag/metrics/survival_metrics.py
miacag/model_utils/GradCam_model.py
miacag/model_utils/__init__.py
miacag/model_utils/eval_utils.py
miacag/model_utils/get_loss_func.py
miacag/model_utils/get_optimizer.py
miacag/model_utils/get_test_pipeline.py
miacag/model_utils/grad_cam_utils.py
miacag-0.0.83.dist-info/LICENSE
miacag-0.0.83.dist-info/METADATA
miacag-0.0.83.dist-info/WHEEL
miacag-0.0.83.dist-info/top_level.txt
miacag-0.0.83.dist-info/RECORD
