Metadata-Version: 2.1
Name: miacag
Version: 0.0.83
Summary: miacag angio DL tools
Home-page: https://github.com/ChristianEschen/miacag
Author: Christian Eschen
Author-email: christian_eschen@hotmail.com
Classifier: Programming Language :: Python :: 3
Classifier: License :: OSI Approved :: MIT License
Classifier: Operating System :: OS Independent
Requires-Python: >=3.7
License-File: LICENSE
